babble/Dockerfile
babble/__init__.py
babble/entry.py
babble/providers/main.tf
babble/scripts/activate.py
babble/scripts/create.py
babble/scripts/deactivate.py
babble/scripts/delete.py
babble/scripts/entrypoint.py
babble/scripts/util.py
babble/scripts/view.py
babble/templates/aws/function.py
babble/templates/aws/layer.py
babble/templates/aws/main.tf
babble_cloud_cli-0.1.21.dist-info/WHEEL
babble_cloud_cli-0.1.21.dist-info/entry_points.txt
babble_cloud_cli-0.1.21.dist-info/METADATA
babble_cloud_cli-0.1.21.dist-info/RECORD
