Metadata-Version: 2.1
Name: babble-cloud-cli
Version: 0.1.21
Summary: serverless applications made easy
Author: mkearney2023
Author-email: mkearney2023@gmail.com
Requires-Python: >=3.7.2,<4.0
Classifier: Programming Language :: Python :: 3
Classifier: Programming Language :: Python :: 3.8
Classifier: Programming Language :: Python :: 3.9
Classifier: Programming Language :: Python :: 3.10
Classifier: Programming Language :: Python :: 3.11
Requires-Dist: simple-term-menu (==1.6.1)
Requires-Dist: yaspin (==2.3.0)
